Bilogger.py
Bilogger_Bi2Nb9O3-0.0.1.dist-info/LICENSE
Bilogger_Bi2Nb9O3-0.0.1.dist-info/METADATA
Bilogger_Bi2Nb9O3-0.0.1.dist-info/WHEEL
Bilogger_Bi2Nb9O3-0.0.1.dist-info/top_level.txt
Bilogger_Bi2Nb9O3-0.0.1.dist-info/RECORD
