Metadata-Version: 2.1
Name: Bilogger-Bi2Nb9O3
Version: 0.0.1
Summary: A simple logging tool
Author-email: Bi2Nb9O3 <1022780532@qq.com>
Project-URL: Homepage, https://github.com/Bi2Nb9O3-Studio/Bilogger
Project-URL: Bug Tracker, https://github.com/Bi2Nb9O3-Studio/Bilogger/issues
Classifier: Programming Language :: Python :: 3
Classifier: License :: OSI Approved :: MIT License
Classifier: Operating System :: OS Independent
Requires-Python: >=3.7
License-File: LICENSE
